feature_grouper/__init__.py
feature_grouper/feature_grouper.py
feature_grouper-0.1.2.dist-info/LICENSE.md
feature_grouper-0.1.2.dist-info/WHEEL
feature_grouper-0.1.2.dist-info/METADATA
feature_grouper-0.1.2.dist-info/RECORD
